LICENSE
MANIFEST.in
README.rst
setup.cfg
setup.py
cachefly/__init__.py
cachefly.egg-info/PKG-INFO
cachefly.egg-info/SOURCES.txt
cachefly.egg-info/dependency_links.txt
cachefly.egg-info/requires.txt
cachefly.egg-info/top_level.txt
cachefly.egg-info/zip-safe
django_cachefly/__init__.py
django_cachefly/models.py