Metadata-Version: 1.1
Name: cachefly
Version: 1.0.0
Summary: Convenient CacheFly CDN management for Python
Home-page: http://bruun.co/
Author: Nick Bruun
Author-email: nick@bruun.co
License: Copyright 2013 Nick Bruun <nick@bruun.co>
